FileTransforms/BaseTransforms.py
FileTransforms/ColumnMod.py
FileTransforms/Exceptions.py
FileTransforms/FileType.py
FileTransforms/FixedWidthTextParser.py
FileTransforms/Result.py
FileTransforms/Transform.py
FileTransforms/__init__.py
FileTransforms/csv_utils.py
FileTransforms/header_utils.py
tests/__init__.py
tests/test_BaseTransforms.py
tests/test_FixedWidthTextParser.py
tests/test_Result.py
tests/test_utils.py
FileTransforms-0.2.1.dist-info/LICENSE
FileTransforms-0.2.1.dist-info/METADATA
FileTransforms-0.2.1.dist-info/WHEEL
FileTransforms-0.2.1.dist-info/top_level.txt
FileTransforms-0.2.1.dist-info/RECORD
