Metadata-Version: 2.1
Name: FileTransforms
Version: 0.2.1
Summary: A library for easily transforming files
Home-page: http://github.com/kallam/FileTransforms
Author: Alex Kallam
License: MIT
Platform: UNKNOWN
Classifier: Programming Language :: Python :: 3
Classifier: License :: OSI Approved :: MIT License
Classifier: Operating System :: OS Independent
Provides-Extra: dev
Requires-Dist: pytest; extra == 'dev'
Provides-Extra: xlsx
Requires-Dist: pandas; extra == 'xlsx'
